Workbook

Sheet ACCEUIL
A1: 📓 GESTION DU BUDGET MENSUEL
A3: Suivez, analysez votre budget chauqe mois
A5: 🧭 Comment utiliser ce fichier
A6: 1 | B6: Commencez par l’onglet BUDGET_MENSUEL. | C6: Saisissez vos opérations : date, type, catégorie, description, montant et mode de paiement.
A7: 2 | B7: Utilisez les menus déroulants. | C7: Ils réduisent les erreurs de saisie et gardent vos données propres.
A8: 3 | B8: Définissez vos limites. | C8: Dans BUDGET_PREVISIONNEL, indiquez le budget prévu pour chaque catégorie.
A9: 4 | B9: Consultez le tableau de bord. | C9: Sélectionnez le mois et visualisez automatiquement revenus, dépenses, solde et graphiques.
A10: 5 | B10: Ne modifiez pas les formules. | C10: Les cellules calculées sont là pour automatiser votre suivi.
A11: 🎨 Code couleur
B13: Cellule à remplir (saisie manuelle)
B14: Cellule calculée automatiquement — ne pas modifier

Sheet CATEGORIE
A1: CATHEGORIE REVENUS | B1: CATEGORIE DEPENSES
A2: Salaire | B2: Logement
A3: Business/Vente | B3: Alimentation
A4: Freelance | B4: Transport
A5: Investissements | B5: Communication
A6: Immobilier | B6: Santé
A7: Aides et tranferts | B7: Education
A8: Autres revenus | B8: Commerce/Activité
B9: Personnel
B10: Famille et Social
B11: Loisir
B12: Finance
B13: Epargne et investissement
B14: Impôts et Taxe
B15: Facture
B16: Autre dépenses
A19: © Votre Boutique — Journal de Trading Professionnel

Sheet BUDGET_MENSUEL
A1: DATE | B1: TYPE | C1: CATEGORIE | D1: DESCRIPTION | E1: MONTANT | F1: MOIS | G1: CUMUL
B2: Revenu | C2: Business/Vente | E2: 1000000 | F2: =IF(A2="","",TEXT(A2,"mmmm yyyy")) | G2: =IF(A2="","",IF(B2="Revenu",E2,-E2))
B3: Dépense | C3: Logement | E3: 500000 | F3: =IF(A3="","",TEXT(A3,"mmmm yyyy")) | G3: =IFERROR(IF(A3="","",(IF(B3="Revenu",E3,-E3))+G2),"")
B4: Revenu | C4: Freelance | E4: 5000000 | F4: =IF(A4="","",TEXT(A4,"mmmm yyyy")) | G4: =IFERROR(IF(A4="","",IF(B4="Revenu",E4,-E4))+G3,"")
B5: Dépense | C5: Communication | E5: 10000 | F5: =IF(A5="","",TEXT(A5,"mmmm yyyy")) | G5: =IFERROR(IF(A5="","",IF(B5="Revenu",E5,-E5))+G4,"")
B6: Dépense | C6: Logement | E6: 500000 | F6: =IF(A6="","",TEXT(A6,"mmmm yyyy")) | G6: =IFERROR(IF(A6="","",IF(B6="Revenu",E6,-E6))+G5,"")
F7: =IF(A7="","",TEXT(A7,"mmmm yyyy")) | G7: =IFERROR(IF(A7="","",IF(B7="Revenu",E7,-E7))+G6,"")
F8: =IF(A8="","",TEXT(A8,"mmmm yyyy")) | G8: =IFERROR(IF(A8="","",IF(B8="Revenu",E8,-E8))+G7,"")
F9: =IF(A9="","",TEXT(A9,"mmmm yyyy")) | G9: =IFERROR(IF(A9="","",IF(B9="Revenu",E9,-E9))+G8,"")
F10: =IF(A10="","",TEXT(A10,"mmmm yyyy")) | G10: =IFERROR(IF(A10="","",IF(B10="Revenu",E10,-E10))+G9,"")
F11: =IF(A11="","",TEXT(A11,"mmmm yyyy")) | G11: =IFERROR(IF(A11="","",IF(B11="Revenu",E11,-E11))+G10,"")
F12: =IF(A12="","",TEXT(A12,"mmmm yyyy")) | G12: =IFERROR(IF(A12="","",IF(B12="Revenu",E12,-E12))+G11,"")
F13: =IF(A13="","",TEXT(A13,"mmmm yyyy")) | G13: =IFERROR(IF(A13="","",IF(B13="Revenu",E13,-E13))+G12,"")
F14: =IF(A14="","",TEXT(A14,"mmmm yyyy")) | G14: =IFERROR(IF(A14="","",IF(B14="Revenu",E14,-E14))+G13,"")
F15: =IF(A15="","",TEXT(A15,"mmmm yyyy")) | G15: =IFERROR(IF(A15="","",IF(B15="Revenu",E15,-E15))+G14,"")
F16: =IF(A16="","",TEXT(A16,"mmmm yyyy")) | G16: =IFERROR(IF(A16="","",IF(B16="Revenu",E16,-E16))+G15,"")
F17: =IF(A17="","",TEXT(A17,"mmmm yyyy")) | G17: =IFERROR(IF(A17="","",IF(B17="Revenu",E17,-E17))+G16,"")
F18: =IF(A18="","",TEXT(A18,"mmmm yyyy")) | G18: =IFERROR(IF(A18="","",IF(B18="Revenu",E18,-E18))+G17,"")
... F200: =IF(A200="","",TEXT(A200,"mmmm yyyy")) | G200: =IFERROR(IF(A200="","",IF(B200="Revenu",E200,-E200))+G199,"")

Sheet BUDJET_PREVISIONNEL
A2: Catégorie | B2: Budget prévu | C2: Dépenses réelles | D2: Écart | E2: % utilisé | F2: Statut
A3: Logement | B3: 1000000 | C3: =SUMIFS(BUDGET_MENSUEL!$E$2:$E$200,BUDGET_MENSUEL!$C$2:$C$200,A3,BUDGET_MENSUEL!$B$2:$B$200,"Dépense") -> 1000000 | D3: =B3-C3 -> 0 | E3: =IFERROR(C3/B3,0) -> 1 | F3: =IF(B3=0,"À définir",IF(C3<=B3,"OK","DÉPASSÉ")) -> OK
A4: Alimentation | B4: 500000 | C4: =SUMIFS(BUDGET_MENSUEL!$E$2:$E$200,BUDGET_MENSUEL!$C$2:$C$200,A4,BUDGET_MENSUEL!$B$2:$B$200,"Dépense") -> 0 | D4: =B4-C4 -> 500000 | E4: =IFERROR(C4/B4,0) -> 0 | F4: =IF(B4=0,"À définir",IF(C4<=B4,"OK","DÉPASSÉ")) -> OK
A5: Transport | B5: 100000 | C5: =SUMIFS(BUDGET_MENSUEL!$E$2:$E$200,BUDGET_MENSUEL!$C$2:$C$200,A5,BUDGET_MENSUEL!$B$2:$B$200,"Dépense") -> 0 | D5: =B5-C5 -> 100000 | E5: =IFERROR(C5/B5,0) -> 0 | F5: =IF(B5=0,"À définir",IF(C5<=B5,"OK","DÉPASSÉ")) -> OK
A6: Santé | B6: 10000 | C6: =SUMIFS(BUDGET_MENSUEL!$E$2:$E$200,BUDGET_MENSUEL!$C$2:$C$200,A6,BUDGET_MENSUEL!$B$2:$B$200,"Dépense") -> 0 | D6: =B6-C6 -> 10000 | E6: =IFERROR(C6/B6,0) -> 0 | F6: =IF(B6=0,"À définir",IF(C6<=B6,"OK","DÉPASSÉ")) -> OK
A7: Éducation | B7: 500000 | C7: =SUMIFS(BUDGET_MENSUEL!$E$2:$E$200,BUDGET_MENSUEL!$C$2:$C$200,A7,BUDGET_MENSUEL!$B$2:$B$200,"Dépense") -> 0 | D7: =B7-C7 -> 500000 | E7: =IFERROR(C7/B7,0) -> 0 | F7: =IF(B7=0,"À définir",IF(C7<=B7,"OK","DÉPASSÉ")) -> OK
A8: Communication | B8: 50000 | C8: =SUMIFS(BUDGET_MENSUEL!$E$2:$E$200,BUDGET_MENSUEL!$C$2:$C$200,A8,BUDGET_MENSUEL!$B$2:$B$200,"Dépense") -> 10000 | D8: =B8-C8 -> 40000 | E8: =IFERROR(C8/B8,0) -> 0.2 | F8: =IF(B8=0,"À définir",IF(C8<=B8,"OK","DÉPASSÉ")) -> OK
A9: Loisirs | B9: 10000 | C9: =SUMIFS(BUDGET_MENSUEL!$E$2:$E$200,BUDGET_MENSUEL!$C$2:$C$200,A9,BUDGET_MENSUEL!$B$2:$B$200,"Dépense") -> 0 | D9: =B9-C9 -> 10000 | E9: =IFERROR(C9/B9,0) -> 0 | F9: =IF(B9=0,"À définir",IF(C9<=B9,"OK","DÉPASSÉ")) -> OK
A10: Shopping | B10: 10000 | C10: =SUMIFS(BUDGET_MENSUEL!$E$2:$E$200,BUDGET_MENSUEL!$C$2:$C$200,A10,BUDGET_MENSUEL!$B$2:$B$200,"Dépense") -> 0 | D10: =B10-C10 -> 10000 | E10: =IFERROR(C10/B10,0) -> 0 | F10: =IF(B10=0,"À définir",IF(C10<=B10,"OK","DÉPASSÉ")) -> OK
A11: Dette/Crédit | B11: 5000000 | C11: =SUMIFS(BUDGET_MENSUEL!$E$2:$E$200,BUDGET_MENSUEL!$C$2:$C$200,A11,BUDGET_MENSUEL!$B$2:$B$200,"Dépense") -> 0 | D11: =B11-C11 -> 5000000 | E11: =IFERROR(C11/B11,0) -> 0 | F11: =IF(B11=0,"À définir",IF(C11<=B11,"OK","DÉPASSÉ")) -> OK
A12: Épargne | B12: 1000000 | C12: =SUMIFS(BUDGET_MENSUEL!$E$2:$E$200,BUDGET_MENSUEL!$C$2:$C$200,A12,BUDGET_MENSUEL!$B$2:$B$200,"Dépense") -> 0 | D12: =B12-C12 -> 1000000 | E12: =IFERROR(C12/B12,0) -> 0 | F12: =IF(B12=0,"À définir",IF(C12<=B12,"OK","DÉPASSÉ")) -> OK
A13: Abonnements | B13: 15000 | C13: =SUMIFS(BUDGET_MENSUEL!$E$2:$E$200,BUDGET_MENSUEL!$C$2:$C$200,A13,BUDGET_MENSUEL!$B$2:$B$200,"Dépense") -> 0 | D13: =B13-C13 -> 15000 | E13: =IFERROR(C13/B13,0) -> 0 | F13: =IF(B13=0,"À définir",IF(C13<=B13,"OK","DÉPASSÉ")) -> OK
A14: Autre dépense | B14: 1000000 | C14: =SUMIFS(BUDGET_MENSUEL!$E$2:$E$200,BUDGET_MENSUEL!$C$2:$C$200,A14,BUDGET_MENSUEL!$B$2:$B$200,"Dépense") -> 0 | D14: =B14-C14 -> 1000000 | E14: =IFERROR(C14/B14,0) -> 0 | F14: =IF(B14=0,"À définir",IF(C14<=B14,"OK","DÉPASSÉ")) -> OK

Sheet TABLEAU_DE_BORD
G1: INDICATEURS | H1: VALEUR | AG1: DATE | AH1: CUMUL
G2: Total Revenus | H2: =SUMIF(BUDGET_MENSUEL!B2:B200,"Revenu",BUDGET_MENSUEL!E2:E200) -> 6000000 | AG2: =IF(Tableau6[[#This Row],[DATE ]]="","",Tableau6[[#This Row],[DATE ]]) | AH2: =Tableau6[[#This Row],[CUMUL]]
G3: Total Dépenses | H3: =SUMIF(BUDGET_MENSUEL!B2:B200,"Dépense",BUDGET_MENSUEL!E2:E200) -> 1010000 | AG3: =IF(Tableau6[[#This Row],[DATE ]]="","",Tableau6[[#This Row],[DATE ]]) | AH3: =Tableau6[[#This Row],[CUMUL]]
G4: Solde | H4: =H2-H3 -> 4990000 | AG4: =IF(Tableau6[[#This Row],[DATE ]]="","",Tableau6[[#This Row],[DATE ]]) | AH4: =Tableau6[[#This Row],[CUMUL]]
G5: Taux d'épargne | H5: =IFERROR(H4/H2,"") -> 0.83166667 | AG5: =IF(Tableau6[[#This Row],[DATE ]]="","",Tableau6[[#This Row],[DATE ]]) | AH5: =Tableau6[[#This Row],[CUMUL]]
G6: Nombre de movements | H6: =COUNTIF(BUDGET_MENSUEL!B2:B200,"Revenu")+COUNTIF(BUDGET_MENSUEL!B2:B200,"Dépense") -> 5 | AG6: =IF(Tableau6[[#This Row],[DATE ]]="","",Tableau6[[#This Row],[DATE ]]) | AH6: =Tableau6[[#This Row],[CUMUL]]
AG7: =IF(Tableau6[[#This Row],[DATE ]]="","",Tableau6[[#This Row],[DATE ]]) | AH7: =Tableau6[[#This Row],[CUMUL]]
AG8: =IF(Tableau6[[#This Row],[DATE ]]="","",Tableau6[[#This Row],[DATE ]]) | AH8: =Tableau6[[#This Row],[CUMUL]]
AG9: =IF(Tableau6[[#This Row],[DATE ]]="","",Tableau6[[#This Row],[DATE ]]) | AH9: =Tableau6[[#This Row],[CUMUL]]
AG10: =IF(Tableau6[[#This Row],[DATE ]]="","",Tableau6[[#This Row],[DATE ]]) | AH10: =Tableau6[[#This Row],[CUMUL]]
AG11: =IF(Tableau6[[#This Row],[DATE ]]="","",Tableau6[[#This Row],[DATE ]]) | AH11: =Tableau6[[#This Row],[CUMUL]]
AG12: =IF(Tableau6[[#This Row],[DATE ]]="","",Tableau6[[#This Row],[DATE ]]) | AH12: =Tableau6[[#This Row],[CUMUL]]
AG13: =IF(Tableau6[[#This Row],[DATE ]]="","",Tableau6[[#This Row],[DATE ]]) | AH13: =Tableau6[[#This Row],[CUMUL]]
AG14: =IF(Tableau6[[#This Row],[DATE ]]="","",Tableau6[[#This Row],[DATE ]]) | AH14: =Tableau6[[#This Row],[CUMUL]]
AG15: =IF(Tableau6[[#This Row],[DATE ]]="","",Tableau6[[#This Row],[DATE ]]) | AH15: =Tableau6[[#This Row],[CUMUL]]
AG16: =IF(Tableau6[[#This Row],[DATE ]]="","",Tableau6[[#This Row],[DATE ]]) | AH16: =Tableau6[[#This Row],[CUMUL]]
AG17: =IF(Tableau6[[#This Row],[DATE ]]="","",Tableau6[[#This Row],[DATE ]]) | AH17: =Tableau6[[#This Row],[CUMUL]]
AG18: =IF(Tableau6[[#This Row],[DATE ]]="","",Tableau6[[#This Row],[DATE ]]) | AH18: =Tableau6[[#This Row],[CUMUL]]
... AG199: =IF(Tableau6[[#This Row],[DATE ]]="","",Tableau6[[#This Row],[DATE ]]) | AH199: =Tableau6[[#This Row],[CUMUL]]
AG200: =IF(Tableau6[[#This Row],[DATE ]]="","",Tableau6[[#This Row],[DATE ]])
